CONTRIBUTING.md
MANIFEST.in
README.rst
setup.py
bin/terminal_velocity
terminal_velocity/__init__.py
terminal_velocity/notebook.py
terminal_velocity/urwid_ui.py
terminal_velocity.egg-info/PKG-INFO
terminal_velocity.egg-info/SOURCES.txt
terminal_velocity.egg-info/dependency_links.txt
terminal_velocity.egg-info/requires.txt
terminal_velocity.egg-info/top_level.txt