Metadata-Version: 1.0
Name: terminal-velocity
Version: 0.1a8
Summary: A fast note-taking app for the UNIX terminal
Home-page: http://seanh.github.com/terminal_velocity/
Author: Sean Hammond
Author-email: UNKNOWN
License: GNU General Public License, Version 3
Platform: UNKNOWN
